{"750":{"defs":"","body":"<g transform=\"matrix(1 0 0 1 0 0)\"><path d=\"M21.65 -6.25Q23.35 -6.55 24.80 -4.35Q26.15 -2.20 26.15 0.40Q26.15 2.35 25.05 3.10Q24.45 3.45 23.05 3.60L20.25 3.60L19.40 3.30Q19.00 3.65 18.60 3.80L16.25 3.95Q14.40 3.70 13.60 3.00L13.45 2.90Q12.50 4.25 10.85 4.65L8.15 4.70L5.50 3.85L4.70 3.20L4.10 2.95L2.95 4.00L1.40 4.85L-0.25 5.10L-1.95 4.95L-3.95 4.75L-5.25 4.05L-6.75 4.55Q-8.25 4.80 -9.35 3.80L-10.40 4.45L-11.45 4.90L-12.50 4.95L-14.15 4.65Q-14.80 4.50 -15.65 3.75L-16.20 3.15L-16.45 3.30L-17.75 4.15Q-18.85 4.85 -19.65 4.85L-21.45 4.35L-22.80 3.60L-23.75 2.65L-25.00 0.85L-25.15 -0.90L-25.10 -3.35L-24.95 -4.45L-24.25 -5.60L-22.30 -7.05L-19.90 -7.40Q-18.90 -7.20 -17.75 -6.60L-16.85 -6.60L-15.45 -7.65L-13.20 -7.90Q-11.80 -7.80 -10.45 -6.95L-8.60 -8.25L-6.25 -8.35Q-4.85 -8.20 -4.15 -7.70L-3.55 -7.15Q-2.70 -7.75 -1.55 -7.95L0.90 -7.80L1.40 -7.55L2.50 -7.50L3.30 -7.85L5.00 -8.15L6.65 -7.95L8.05 -7.05L8.30 -7.00L8.40 -7.10Q9.50 -7.70 10.60 -7.60Q11.65 -7.50 12.85 -6.60L13.50 -6.80L13.85 -7.10Q14.90 -7.75 15.80 -7.90L16.60 -7.90L18.25 -7.75L20.25 -7.00L21.25 -6.10L21.65 -6.25Z\" fill=\"rgb(0,0,0)\" fill-rule=\"evenodd\"/></g>"},"751":{"defs":"","body":"<g transform=\"matrix(1 0 0 1 0 0)\"><path d=\"M-9.90 15.65L-14.10 15.95Q-16.45 15.85 -18.00 14.90Q-19.95 13.75 -20.65 11.30Q-21.35 9.00 -20.65 6.65Q-19.45 2.75 -14.90 -0.40Q-8.05 -5.10 1.85 -5.35Q9.55 -5.50 19.20 -2.50Q22.55 -1.55 24.05 -0.20Q25.60 1.10 26.60 3.70Q28.35 8.55 26.75 12.80Q25.90 15.00 24.20 16.65Q22.45 18.30 20.25 18.95Q17.75 19.60 14.35 19.00L8.60 17.60L2.85 16.05L-9.90 15.65ZM-3.55 1.80Q-7.70 2.75 -9.75 3.90Q-13.10 5.65 -14.30 8.40Q-14.60 8.85 -14.45 9.20Q-14.20 9.75 -13.10 9.65L-5.40 9.10L2.25 9.45L9.25 11.10L16.25 12.85L19.10 12.70Q20.15 12.25 20.80 10.75Q21.65 9.00 21.35 7.30Q21.10 5.35 19.55 4.40L17.35 3.60L10.60 1.90L5.20 1.05Q2.20 0.75 -0.20 1.10L-3.55 1.80Z\" fill=\"rgb(0,0,0)\" fill-rule=\"evenodd\"/><path d=\"M-9.75 3.90Q-7.70 2.75 -3.55 1.80L-0.20 1.10Q2.20 0.75 5.20 1.05L10.60 1.90L17.35 3.60L19.55 4.40Q21.10 5.35 21.35 7.30Q21.65 9.00 20.80 10.75Q20.15 12.25 19.10 12.70L16.25 12.85L9.25 11.10L2.25 9.45L-5.40 9.10L-13.10 9.65Q-14.20 9.75 -14.45 9.20Q-14.60 8.85 -14.30 8.40Q-13.10 5.65 -9.75 3.90Z\" fill=\"rgb(166,145,133)\" fill-rule=\"evenodd\"/></g>"},"752":{"defs":"","body":""},"753":{"defs":"","body":""},"754":{"defs":"","body":""},"755":{"defs":"","body":""},"756":{"defs":"","body":""},"757":{"defs":"","body":""},"758":{"defs":"","body":""},"759":{"defs":"","body":""},"760":{"defs":"","body":""},"761":{"defs":"","body":""},"762":{"defs":"","body":""},"763":{"defs":"","body":""},"764":{"defs":"","body":""},"765":{"defs":"","body":""},"766":{"defs":"","body":""},"767":{"defs":"","body":""},"768":{"defs":"","body":""},"769":{"defs":"","body":""},"770":{"defs":"","body":""},"771":{"defs":"","body":""},"772":{"defs":"","body":""},"773":{"defs":"","body":""},"774":{"defs":"","body":""},"775":{"defs":"","body":""},"776":{"defs":"","body":""},"777":{"defs":"","body":""},"778":{"defs":"","body":""},"779":{"defs":"","body":""},"780":{"defs":"","body":""},"781":{"defs":"","body":""},"782":{"defs":"","body":""},"783":{"defs":"","body":""},"784":{"defs":"","body":""},"785":{"defs":"","body":""},"786":{"defs":"","body":""},"787":{"defs":"","body":""},"788":{"defs":"","body":""},"789":{"defs":"","body":""},"790":{"defs":"","body":""},"791":{"defs":"","body":""},"792":{"defs":"","body":""},"793":{"defs":"","body":""},"794":{"defs":"","body":""},"795":{"defs":"","body":""},"796":{"defs":"","body":""},"797":{"defs":"","body":""},"798":{"defs":"","body":""},"799":{"defs":"","body":""},"800":{"defs":"","body":""},"801":{"defs":"","body":""},"802":{"defs":"","body":""},"803":{"defs":"","body":""},"804":{"defs":"","body":""},"805":{"defs":"","body":""},"806":{"defs":"","body":""},"807":{"defs":"","body":""},"808":{"defs":"","body":""},"809":{"defs":"","body":""},"810":{"defs":"","body":""},"811":{"defs":"","body":""},"812":{"defs":"","body":""},"813":{"defs":"","body":""},"814":{"defs":"","body":""},"815":{"defs":"","body":""},"816":{"defs":"","body":""},"817":{"defs":"","body":""},"818":{"defs":"","body":""},"819":{"defs":"","body":""},"820":{"defs":"","body":""},"821":{"defs":"","body":""},"822":{"defs":"","body":""},"823":{"defs":"","body":""},"824":{"defs":"","body":""},"825":{"defs":"","body":""},"826":{"defs":"","body":""},"827":{"defs":"","body":""},"828":{"defs":"","body":""},"829":{"defs":"","body":""},"830":{"defs":"","body":""},"831":{"defs":"","body":""},"832":{"defs":"","body":""},"833":{"defs":"","body":""},"834":{"defs":"","body":""},"835":{"defs":"","body":""},"836":{"defs":"","body":""},"837":{"defs":"","body":""},"838":{"defs":"","body":""},"839":{"defs":"","body":""},"840":{"defs":"","body":""},"841":{"defs":"","body":""},"842":{"defs":"","body":""},"843":{"defs":"","body":""},"844":{"defs":"","body":""},"845":{"defs":"","body":""},"846":{"defs":"","body":""},"847":{"defs":"","body":""},"848":{"defs":"","body":""},"849":{"defs":"","body":""},"850":{"defs":"","body":""},"851":{"defs":"","body":""},"852":{"defs":"","body":""},"853":{"defs":"","body":""},"854":{"defs":"","body":""},"855":{"defs":"","body":""},"856":{"defs":"","body":""},"857":{"defs":"","body":""},"858":{"defs":"","body":""},"859":{"defs":"","body":""},"860":{"defs":"","body":""},"861":{"defs":"","body":""},"862":{"defs":"","body":""},"863":{"defs":"","body":""},"864":{"defs":"","body":""},"865":{"defs":"","body":""},"866":{"defs":"","body":""},"867":{"defs":"","body":""},"868":{"defs":"","body":""},"869":{"defs":"","body":""},"870":{"defs":"","body":""},"871":{"defs":"","body":""},"872":{"defs":"","body":""},"873":{"defs":"","body":""},"874":{"defs":"","body":""},"875":{"defs":"","body":""},"876":{"defs":"","body":""},"877":{"defs":"","body":""},"878":{"defs":"","body":""},"879":{"defs":"","body":""},"880":{"defs":"","body":""},"881":{"defs":"","body":""},"882":{"defs":"","body":""},"883":{"defs":"","body":""},"884":{"defs":"","body":""},"885":{"defs":"","body":""},"886":{"defs":"","body":""},"887":{"defs":"","body":""},"888":{"defs":"","body":""},"889":{"defs":"","body":""},"890":{"defs":"","body":""},"891":{"defs":"","body":""},"892":{"defs":"","body":""},"893":{"defs":"","body":""},"894":{"defs":"","body":""},"895":{"defs":"","body":""},"896":{"defs":"","body":""},"897":{"defs":"","body":""},"898":{"defs":"","body":""},"899":{"defs":"","body":""}}